README.rst
setup.cfg
setup.py
src/isign/__init__.py
src/isign/client.py
src/isign/connection.py
src/isign/environment.py
src/isign/error.py
src/isign/functions.py
src/isign/model/__init__.py
src/isign/model/base.py
src/isign/model/certificate.py
src/isign/model/error.py
src/isign/model/field_error.py
src/isign/model/file.py
src/isign/model/mobile_certificate_response.py
src/isign/model/mobile_login_response.py
src/isign/model/mobile_sign_response.py
src/isign/model/parsed.py
src/isign/model/pdf.py
src/isign/model/response.py
src/python_isign.egg-info/PKG-INFO
src/python_isign.egg-info/SOURCES.txt
src/python_isign.egg-info/dependency_links.txt
src/python_isign.egg-info/requires.txt
src/python_isign.egg-info/top_level.txt