Metadata-Version: 1.1
Name: python-isign
Version: 0.3.0
Summary: Python client for isign.io API.
Home-page: https://github.com/Paulius-Maruska/python-isign
Author: Paulius Maruška
Author-email: paulius.maruska@gmail.com
License: MIT
Keywords: isign,client
Platform: UNKNOWN
Classifier: Development Status :: 4 - Beta
Classifier: Intended Audience :: Developers
Classifier: License :: OSI Approved :: MIT License
Classifier: Operating System :: OS Independent
Classifier: Programming Language :: Python :: 3.6
Classifier: Programming Language :: Python :: 3 :: Only
Classifier: Topic :: Security
Classifier: Topic :: Software Development :: Libraries
